CHANGELOG
COPYRIGHT
INSTALL
LICENSE
MANIFEST.in
README
setup.py
seur/__init__.py
seur/__init__.pyc
seur/api.py
seur/api.pyc
seur/picking.py
seur/picking.pyc
seur/utils.py
seur.egg-info/PKG-INFO
seur.egg-info/SOURCES.txt
seur.egg-info/dependency_links.txt
seur.egg-info/requires.txt
seur.egg-info/top_level.txt
seur/template/city.xml
seur/template/manifiesto.xml
seur/template/picking_info.xml
seur/template/picking_label.xml
seur/template/picking_label_pdf.xml
seur/template/picking_list.xml
seur/template/picking_send.xml
seur/template/picking_send_pdf.xml
seur/template/test_connection.xml
seur/template/zip.xml